filegardener.py
filegardener-1.6.9.data/data/test_data/.gitignore
filegardener-1.6.9.data/data/test_data/AUTHORS.rst
filegardener-1.6.9.data/data/test_data/CONTRIBUTING.md
filegardener-1.6.9.data/data/test_data/DIRECTORIES.txt
filegardener-1.6.9.data/data/test_data/HISTORY.rst
filegardener-1.6.9.data/data/test_data/LICENSE
filegardener-1.6.9.data/data/test_data/MANIFEST.in
filegardener-1.6.9.data/data/test_data/Makefile
filegardener-1.6.9.data/data/test_data/NOTICE
filegardener-1.6.9.data/data/test_data/PKG-INFO
filegardener-1.6.9.data/data/test_data/README.rst
filegardener-1.6.9.data/data/test_data/SOURCES.txt
filegardener-1.6.9.data/data/test_data/VERSION
filegardener-1.6.9.data/data/test_data/__init__.py
filegardener-1.6.9.data/data/test_data/__init__.pyc
filegardener-1.6.9.data/data/test_data/_collections.py
filegardener-1.6.9.data/data/test_data/_collections.pyc
filegardener-1.6.9.data/data/test_data/_implementation.py
filegardener-1.6.9.data/data/test_data/adapters.py
filegardener-1.6.9.data/data/test_data/adapters.pyc
filegardener-1.6.9.data/data/test_data/advanced.rst
filegardener-1.6.9.data/data/test_data/afile
filegardener-1.6.9.data/data/test_data/api.py
filegardener-1.6.9.data/data/test_data/api.pyc
filegardener-1.6.9.data/data/test_data/api.rst
filegardener-1.6.9.data/data/test_data/appengine.py
filegardener-1.6.9.data/data/test_data/auth.py
filegardener-1.6.9.data/data/test_data/auth.pyc
filegardener-1.6.9.data/data/test_data/authentication.rst
filegardener-1.6.9.data/data/test_data/bfile
filegardener-1.6.9.data/data/test_data/big5freq.py
filegardener-1.6.9.data/data/test_data/big5prober.py
filegardener-1.6.9.data/data/test_data/cacert.pem
filegardener-1.6.9.data/data/test_data/certs.py
filegardener-1.6.9.data/data/test_data/certs.pyc
filegardener-1.6.9.data/data/test_data/chardetect.py
filegardener-1.6.9.data/data/test_data/chardistribution.py
filegardener-1.6.9.data/data/test_data/charsetgroupprober.py
filegardener-1.6.9.dist-info/DESCRIPTION.rst
filegardener-1.6.9.dist-info/METADATA
filegardener-1.6.9.dist-info/RECORD
filegardener-1.6.9.dist-info/WHEEL
filegardener-1.6.9.dist-info/entry_points.txt
filegardener-1.6.9.dist-info/metadata.json
filegardener-1.6.9.dist-info/top_level.txt
