Metadata-Version: 2.0
Name: filegardener
Version: 1.6.9
Summary: filegardener file utilities dedup, only file copy detection, empty dir detection
Home-page: https://github.com/smorin/filegardener
Author: Steve Morin
Author-email: steve@stevemorin.com
License: UNKNOWN
Keywords: dedup,file cleanup,empy dirs,duplicate file detection
Platform: UNKNOWN
Classifier: Programming Language :: Python
Classifier: Programming Language :: Python :: 2
Classifier: Programming Language :: Python :: 2.7
Classifier: Programming Language :: Python :: 3
Classifier: Programming Language :: Python :: 3.4
Classifier: Programming Language :: Python :: 3.5
Classifier: Programming Language :: Python
Classifier: Environment :: Console
Classifier: Intended Audience :: Developers
Classifier: Intended Audience :: Developers
Classifier: Intended Audience :: Information Technology
Classifier: Intended Audience :: System Administrators
Classifier: License :: Other/Proprietary License
Classifier: Operating System :: MacOS
Classifier: Operating System :: POSIX :: Linux
Classifier: Operating System :: Unix
Classifier: Operating System :: POSIX :: BSD
Requires-Dist: Click
